tgfp_nfl/__init__.py
tgfp_nfl/tgfp_nfl.py
tgfp_nfl-6.3.3.dist-info/METADATA
tgfp_nfl-6.3.3.dist-info/WHEEL
tgfp_nfl-6.3.3.dist-info/RECORD
