Metadata-Version: 2.1
Name: tgfp-nfl
Version: 6.3.3
Summary: Python extraction of NFL scores schedule data from abstracted data source
License: MIT
Author: John Sturgeon
Author-email: john.sturgeon@me.com
Requires-Python: >=3.10
Classifier: License :: OSI Approved :: MIT License
Classifier: Programming Language :: Python :: 3
Classifier: Programming Language :: Python :: 3.10
Classifier: Programming Language :: Python :: 3.11
Classifier: Programming Language :: Python :: 3.12
Requires-Dist: httpx (>=0.27.0,<0.28.0)
Requires-Dist: onetoonemap (>=1.0.0,<2.0.0)
Requires-Dist: python-dateutil (>=2.8.2,<3.0.0)
